gcj_rectify_server/__init__.py
gcj_rectify_server/fetch.py
gcj_rectify_server/main.py
gcj_rectify_server/rectify.py
gcj_rectify_server/transform.py
gcj_rectify_server/utils.py
gcj_rectify-0.1.3.dist-info/METADATA
gcj_rectify-0.1.3.dist-info/WHEEL
gcj_rectify-0.1.3.dist-info/entry_points.txt
gcj_rectify-0.1.3.dist-info/licenses/LICENSE
gcj_rectify-0.1.3.dist-info/RECORD
